{
  "$schema": "https://developer.microsoft.com/json-schemas/fabric/item/report/definition/visualContainer/2.4.0/schema.json",
  "name": "c68f3e18a2b2477c41b7",
  "position": {
    "x": 270,
    "y": 15.714285714285715,
    "z": 3000,
    "height": 412.85714285714289,
    "width": 961.42857142857144,
    "tabOrder": 3000
  },
  "visual": {
    "visualType": "lineStackedColumnComboChart",
    "query": {
      "queryState": {
        "Category": {
          "projections": [
            {
              "field": {
                "Column": {
                  "Expression": {
                    "SourceRef": {
                      "Entity": "Date"
                    }
                  },
                  "Property": "Month"
                }
              },
              "queryRef": "Date.Month",
              "nativeQueryRef": "Month",
              "active": true
            }
          ],
          "showAll": true
        },
        "Y": {
          "projections": [
            {
              "field": {
                "Aggregation": {
                  "Expression": {
                    "Column": {
                      "Expression": {
                        "SourceRef": {
                          "Entity": "Sales"
                        }
                      },
                      "Property": "Sales"
                    }
                  },
                  "Function": 0
                }
              },
              "queryRef": "Sum(Sales.Sales)",
              "nativeQueryRef": "Sales",
              "displayName": "Sales"
            }
          ]
        },
        "Y2": {
          "projections": [
            {
              "field": {
                "Measure": {
                  "Expression": {
                    "SourceRef": {
                      "Entity": "Sales"
                    }
                  },
                  "Property": "Profit Margin"
                }
              },
              "queryRef": "Sales.Profit Margin",
              "nativeQueryRef": "Profit Margin"
            }
          ]
        }
      }
    },
    "drillFilterOtherVisuals": true
  }
}